salad_cloud_imds_sdk/__init__.py
salad_cloud_imds_sdk/sdk.py
salad_cloud_imds_sdk/sdk_async.py
salad_cloud_imds_sdk/hooks/__init__.py
salad_cloud_imds_sdk/hooks/hook.py
salad_cloud_imds_sdk/models/__init__.py
salad_cloud_imds_sdk/models/deletion_cost.py
salad_cloud_imds_sdk/models/reallocate_prototype.py
salad_cloud_imds_sdk/models/salad_cloud_imds_error.py
salad_cloud_imds_sdk/models/status.py
salad_cloud_imds_sdk/models/token.py
salad_cloud_imds_sdk/models/utils/__init__.py
salad_cloud_imds_sdk/models/utils/base_model.py
salad_cloud_imds_sdk/models/utils/cast_models.py
salad_cloud_imds_sdk/models/utils/json_map.py
salad_cloud_imds_sdk/models/utils/one_of_base_model.py
salad_cloud_imds_sdk/models/utils/sentinel.py
salad_cloud_imds_sdk/net/__init__.py
salad_cloud_imds_sdk/net/environment/__init__.py
salad_cloud_imds_sdk/net/environment/environment.py
salad_cloud_imds_sdk/net/headers/__init__.py
salad_cloud_imds_sdk/net/headers/base_header.py
salad_cloud_imds_sdk/net/request_chain/__init__.py
salad_cloud_imds_sdk/net/request_chain/request_chain.py
salad_cloud_imds_sdk/net/request_chain/handlers/__init__.py
salad_cloud_imds_sdk/net/request_chain/handlers/base_handler.py
salad_cloud_imds_sdk/net/request_chain/handlers/hook_handler.py
salad_cloud_imds_sdk/net/request_chain/handlers/http_handler.py
salad_cloud_imds_sdk/net/request_chain/handlers/retry_handler.py
salad_cloud_imds_sdk/net/transport/__init__.py
salad_cloud_imds_sdk/net/transport/api_error.py
salad_cloud_imds_sdk/net/transport/request.py
salad_cloud_imds_sdk/net/transport/request_error.py
salad_cloud_imds_sdk/net/transport/response.py
salad_cloud_imds_sdk/net/transport/serializer.py
salad_cloud_imds_sdk/net/transport/utils.py
salad_cloud_imds_sdk/services/__init__.py
salad_cloud_imds_sdk/services/metadata.py
salad_cloud_imds_sdk/services/async_/__init__.py
salad_cloud_imds_sdk/services/async_/metadata.py
salad_cloud_imds_sdk/services/async_/utils/__init__.py
salad_cloud_imds_sdk-0.9.0a5.dist-info/licenses/LICENSE
salad_cloud_imds_sdk-0.9.0a5.dist-info/METADATA
salad_cloud_imds_sdk-0.9.0a5.dist-info/WHEEL
salad_cloud_imds_sdk-0.9.0a5.dist-info/top_level.txt
salad_cloud_imds_sdk-0.9.0a5.dist-info/RECORD
